odoo8_addon_customer_pricing_in_product_view-8.0.1.2.1-py2.7-nspkg.pth
odoo8_addon_customer_pricing_in_product_view-8.0.1.2.1.dist-info/DESCRIPTION.rst
odoo8_addon_customer_pricing_in_product_view-8.0.1.2.1.dist-info/METADATA
odoo8_addon_customer_pricing_in_product_view-8.0.1.2.1.dist-info/RECORD
odoo8_addon_customer_pricing_in_product_view-8.0.1.2.1.dist-info/WHEEL
odoo8_addon_customer_pricing_in_product_view-8.0.1.2.1.dist-info/metadata.json
odoo8_addon_customer_pricing_in_product_view-8.0.1.2.1.dist-info/namespace_packages.txt
odoo8_addon_customer_pricing_in_product_view-8.0.1.2.1.dist-info/top_level.txt
odoo_addons/customer_pricing_in_product_view/README.rst
odoo_addons/customer_pricing_in_product_view/__init__.py
odoo_addons/customer_pricing_in_product_view/__openerp__.py
odoo_addons/customer_pricing_in_product_view/models/__init__.py
odoo_addons/customer_pricing_in_product_view/models/product_pricelist.py
odoo_addons/customer_pricing_in_product_view/models/res_partner.py
odoo_addons/customer_pricing_in_product_view/tests/__init__.py
odoo_addons/customer_pricing_in_product_view/tests/test_customer_pricing_in_product_view.py
odoo_addons/customer_pricing_in_product_view/views/res_partner_view.xml
