Metadata-Version: 2.0
Name: odoo8-addon-customer-pricing-in-product-view
Version: 8.0.1.2.1
Summary: Display Customer Price in Product View
Home-page: http://www.o4sb.com
Author: O4SB - Graeme Gellatly,Odoo Community Association (OCA)
Author-email: support@odoo-community.org
License: AGPL-3
Platform: UNKNOWN
Classifier: Programming Language :: Python :: 2.7
Classifier: Framework :: Odoo
Classifier: License :: OSI Approved :: GNU Affero General Public License v3
Requires-Dist: odoo (<9.0a,>=8.0a)
